imshowtools/__init__.py
imshowtools/helper_functions.py
imshowtools/imshow_functions.py
imshowtools/validation_functions.py
imshowtools-0.6.5.dist-info/LICENCE
imshowtools-0.6.5.dist-info/METADATA
imshowtools-0.6.5.dist-info/WHEEL
imshowtools-0.6.5.dist-info/top_level.txt
imshowtools-0.6.5.dist-info/RECORD
