Metadata-Version: 2.1
Name: imshowtools
Version: 0.6.5
Summary: imshowtools contains simplified imshow functions to show multiple images and with other options
Home-page: https://github.com/saravanabalagi/imshowtools
Author: Saravanabalagi Ramachandran
Author-email: saravanabalagi@hotmail.com
License: MIT
Platform: UNKNOWN
Classifier: Development Status :: 5 - Production/Stable
Classifier: Topic :: Software Development :: Libraries
Classifier: License :: OSI Approved :: MIT License
Classifier: Programming Language :: Python :: 3
Classifier: Programming Language :: Python :: 3.6
Classifier: Programming Language :: Python :: 3.7
Requires-Dist: matplotlib
Requires-Dist: numpy
